annulus/__init__.py
annulus/detector.py
annulus/image.py
annulus-1.0.4.dist-info/METADATA
annulus-1.0.4.dist-info/RECORD
annulus-1.0.4.dist-info/WHEEL
annulus-1.0.4.dist-info/top_level.txt
